{
  "comments": {
    "blockComment": [
      "[-",
      "-]"
    ]
  },
  "brackets": [
    [
      "[",
      "]"
    ],
    [
      "(",
      ")"
    ]
  ],
  // Symbols that are auto-closed when typing
  "autoClosingPairs": [
    [
      "{",
      "}"
    ],
    [
      "[",
      "]"
    ],
    [
      "(",
      ")"
    ],
    [
      "[-",
      "-]"
    ],
    {
      "begin": "\"",
      "end": "\"",
      "notIn": [
        "string"
      ]
    },
    {
      "begin": "'",
      "end": "'",
      "notIn": [
        "string"
      ]
    }
  ],
  // Symbols that can be used to surround a selection
  "surroundingPairs": [
    [
      "{",
      "}"
    ],
    [
      "[",
      "]"
    ],
    [
      "(",
      ")"
    ],
    [
      "\"",
      "\""
    ],
    [
      "'",
      "'"
    ]
  ],
  // An empty array would disable them
  "colorizedBracketPairs": [
    [
      "[",
      "]"
    ]
  ],
  "onEnterRules": [
    {
      "beforeText": "\\[-.*",
      "afterText": "^-*\\]$",
      "action": {
        "indent": "indentOutdent"
      }
    },
    {
      "beforeText": ".*",
      "afterText": "^\\]",
      "action": {
        "indent": "indentOutdent"
      }
    },
    {
      "beforeText": "^\\s*\\[.*",
      "afterText": "^[^\\]]",
      "action": {
        "indent": "indent"
      }
    },
    {
      "beforeText": "^[^\\[].*\\]$",
      "afterText": "\n",
      "action": {
        "indent": "outdent"
      }
    }
  ]
}